sphinx_artisan_theme/__init__.py
sphinx_artisan_theme/ext/__init__.py
sphinx_artisan_theme/ext/extract_toc.py
sphinx_artisan_theme/ext/remove_sections.py
sphinx_artisan_theme/themes/artisan/_macros.html
sphinx_artisan_theme/themes/artisan/domainindex.html
sphinx_artisan_theme/themes/artisan/footer.html
sphinx_artisan_theme/themes/artisan/genindex.html
sphinx_artisan_theme/themes/artisan/globaltoc.html
sphinx_artisan_theme/themes/artisan/header.html
sphinx_artisan_theme/themes/artisan/layout.html
sphinx_artisan_theme/themes/artisan/page.html
sphinx_artisan_theme/themes/artisan/search-field.html
sphinx_artisan_theme/themes/artisan/search.html
sphinx_artisan_theme/themes/artisan/static/theme.css
sphinx_artisan_theme/themes/artisan/static/theme.src.css
sphinx_artisan_theme/themes/artisan/tailwind.config.js
sphinx_artisan_theme/themes/artisan/theme.conf
sphinx_artisan_theme-0.1.0.dist-info/METADATA
sphinx_artisan_theme-0.1.0.dist-info/WHEEL
sphinx_artisan_theme-0.1.0.dist-info/entry_points.txt
sphinx_artisan_theme-0.1.0.dist-info/RECORD
