Metadata-Version: 2.1
Name: sphinx-artisan-theme
Version: 0.1.0
Summary: 
Author: Daniel Knell
Author-email: contact@danielknell.co.uk
Requires-Python: >=3.9,<4.0
Classifier: Programming Language :: Python :: 3
Classifier: Programming Language :: Python :: 3.9
Classifier: Programming Language :: Python :: 3.10
Classifier: Programming Language :: Python :: 3.11
Requires-Dist: Sphinx (>=4.4,<7.0)
